gift_registry/__init__.py
gift_registry/admin.py
gift_registry/apps.py
gift_registry/forms.py
gift_registry/models.py
gift_registry/urls.py
gift_registry/views.py
gift_registry/fixtures/initial_data.json
gift_registry/migrations/0001_initial.py
gift_registry/migrations/__init__.py
gift_registry/static/gift_registry/css/base-1.0.css
gift_registry/static/gift_registry/img/gold-present.jpg
gift_registry/templates/gift_registry/base.html
gift_registry/templates/gift_registry/email_thanks.txt
gift_registry/templates/gift_registry/gift_detail.html
gift_registry/templates/gift_registry/gift_list.html
gift_registry/templates/gift_registry/thanks_cancel.html
gift_registry/templates/gift_registry/thanks_given.html
django_gift_registry-0.5.4.dist-info/COPYING
django_gift_registry-0.5.4.dist-info/METADATA
django_gift_registry-0.5.4.dist-info/WHEEL
django_gift_registry-0.5.4.dist-info/top_level.txt
django_gift_registry-0.5.4.dist-info/RECORD
