Metadata-Version: 2.1
Name: django-gift-registry
Version: 0.5.4
Summary: A minimal wedding registry or gift registry app.
Home-page: https://gitlab.com/BenSturmfels/django-gift-registry
Author: Ben Sturmfels
Author-email: ben@sturm.com.au
License: UNKNOWN
Project-URL: Source, https://gitlab.com/BenSturmfels/django-gift-registry
Project-URL: Bug Reports, https://gitlab.com/BenSturmfels/django-gift-registry/-/issues
Platform: UNKNOWN
Classifier: Development Status :: 4 - Beta
Classifier: Environment :: Web Environment
Classifier: Framework :: Django
Classifier: Intended Audience :: Developers
Classifier: License :: OSI Approved :: Apache Software License
Classifier: Operating System :: OS Independent
Classifier: Programming Language :: Python :: 3.3
Requires-Python: >=3.6
Requires-Dist: Django (>=3.2)
Requires-Dist: Pillow (>=2.5.1)
